executors/__init__.py
executors/__version__.py
executors/commons/__init__.py
executors/exceptions/__init__.py
executors/local/__init__.py
executors/lsf/__init__.py
executors/models/__init__.py
executors/pbsubmit/__init__.py
executors/slurm/__init__.py
executors-0.5.4.dist-info/METADATA
executors-0.5.4.dist-info/WHEEL
executors-0.5.4.dist-info/top_level.txt
executors-0.5.4.dist-info/RECORD
